cerates/__init__.py
cerates/cerates.py
cerates/helpers.py
cerates-0.1.0.dist-info/DESCRIPTION.rst
cerates-0.1.0.dist-info/METADATA
cerates-0.1.0.dist-info/RECORD
cerates-0.1.0.dist-info/WHEEL
cerates-0.1.0.dist-info/metadata.json
cerates-0.1.0.dist-info/top_level.txt
examples/__init__.py
examples/example.py
