Metadata-Version: 1.0
Name: cerates
Version: 0.1.0
Summary: A foreign exchange rates and currency conversion
Home-page: https://github.com/aksbuzz/cerates
Author: Akshay
Author-email: akshayjr69@gmail.com
License: Copyright (c) 2017, Akshay.
